{"player":{"x":596,"y":400,"sprite":"player_front","health":100,"max_health":100,"movement_speed":3.9},"entities":[],"terrain":[{"x":0,"y":0,"width":1,"height":1,"terrain_archetype":"walltl"},{"x":1,"y":0,"width":23,"height":1,"terrain_archetype":"wallt"},{"x":26,"y":0,"width":1,"height":1,"terrain_archetype":"walltr"},{"x":0,"y":1,"width":1,"height":6,"terrain_archetype":"walll"},{"x":0,"y":7,"width":1,"height":1,"terrain_archetype":"wallbl"},{"x":26,"y":1,"width":1,"height":6,"terrain_archetype":"wallr"},{"x":1,"y":7,"width":25,"height":1,"terrain_archetype":"wallb"},{"x":26,"y":7,"width":1,"height":1,"terrain_archetype":"wallbr"},{"x":1,"y":2,"width":23,"height":2,"terrain_archetype":"random_dirt"},{"x":1,"y":1,"width":3,"height":1,"terrain_archetype":"castle_wall_d"},{"x":4,"y":1,"width":1,"height":1,"terrain_archetype":"castle_wall_c"},{"x":8,"y":1,"width":1,"height":1,"terrain_archetype":"castle_wall_c"},{"x":12,"y":1,"width":1,"height":1,"terrain_archetype":"castle_wall_c"},{"x":16,"y":1,"width":1,"height":1,"terrain_archetype":"castle_wall_c"},{"x":20,"y":1,"width":1,"height":1,"terrain_archetype":"castle_wall_c"},{"x":5,"y":1,"width":3,"height":1,"terrain_archetype":"castle_wall_d"},{"x":9,"y":1,"width":3,"height":1,"terrain_archetype":"castle_wall_d"},{"x":13,"y":1,"width":3,"height":1,"terrain_archetype":"castle_wall_d"},{"x":17,"y":1,"width":3,"height":1,"terrain_archetype":"castle_wall_d"},{"x":24,"y":0,"width":1,"height":1,"terrain_archetype":"pillar_top"},{"x":24,"y":1,"width":1,"height":1,"terrain_archetype":"pillar_mid"},{"x":24,"y":2,"width":1,"height":1,"terrain_archetype":"pillar_bot"},{"x":24,"y":7,"width":1,"height":1,"terrain_archetype":"pillar_top2"},{"x":24,"y":6,"width":1,"height":1,"terrain_archetype":"pillar_bot2"},{"x":25,"y":0,"width":1,"height":1,"terrain_archetype":"wallt"},{"x":21,"y":1,"width":3,"height":1,"terrain_archetype":"castle_wall_d"},{"x":25,"y":1,"width":1,"height":1,"terrain_archetype":"castle_wall_d"},{"x":24,"y":3,"width":1,"height":3,"terrain_archetype":"random_dirt"},{"x":25,"y":2,"width":1,"height":5,"terrain_archetype":"random_dirt"},{"x":2,"y":4,"width":22,"height":1,"terrain_archetype":"path"},{"x":1,"y":4,"width":1,"height":1,"terrain_archetype":"random_dirt"},{"x":1,"y":5,"width":23,"height":2,"terrain_archetype":"random_dirt"}]}